CONTRIBUTING.md
LICENSE
MANIFEST.in
README.md
package.xml
requirements.txt
setup.cfg
setup.py
launch/joy_system_manager.launch.py
resource/ros2_system_manager
ros2_system_manager/__init__.py
ros2_system_manager/__main__.py
ros2_system_manager/common.py
ros2_system_manager/exceptions.py
ros2_system_manager/joy2sm.py
ros2_system_manager/ros2_system_manager.py
ros2_system_manager/service.py
ros2_system_manager/system_manager.py
ros2_system_manager.egg-info/PKG-INFO
ros2_system_manager.egg-info/SOURCES.txt
ros2_system_manager.egg-info/dependency_links.txt
ros2_system_manager.egg-info/entry_points.txt
ros2_system_manager.egg-info/requires.txt
ros2_system_manager.egg-info/top_level.txt
ros2_system_manager.egg-info/zip-safe
services/ros2_system_manager.service