Metadata-Version: 2.1
Name: ros2-system-manager
Version: 0.1.5
Summary: ros system manager
Home-page: https://github.com/rbonghi/ros2_system_manager
Author: Raffaello Bonghi
Author-email: raffaello@rnext.it
Maintainer: Raffaello Bonghi
Maintainer-email: raffaello@rnext.it
License: GPLv3
Download-URL: https://github.com/rbonghi/ros2_system_manager/archive/master.zip
Project-URL: How To, https://github.com/rbonghi/ros2_system_manager
Project-URL: Examples, https://github.com/rbonghi/ros2_system_manager/tree/master/examples
Project-URL: Bug Reports, https://github.com/rbonghi/ros2_system_manager/issues
Project-URL: Source, https://github.com/rbonghi/ros2_system_manager/tree/master
Keywords: ros2 foxy system manager
Platform: linux
Platform: linux2
Platform: darwin
Classifier: Development Status :: 4 - Beta
Classifier: Intended Audience :: Developers
Classifier: License :: OSI Approved :: MIT License
Classifier: Programming Language :: Python :: 3
Classifier: Programming Language :: Python :: 3.4
Classifier: Programming Language :: Python :: 3.5
Classifier: Programming Language :: Python :: 3.6
Classifier: Programming Language :: Python :: 3.7
Classifier: Operating System :: POSIX :: Linux
Requires-Python: >=3, <4
